LICENSE
MANIFEST.in
README.md
setup.py
asserts/bunny_cumcubes.png
asserts/bunny_mcubes.png
cumcubes/__init__.py
cumcubes/utils.py
cumcubes/version.py
cumcubes.egg-info/PKG-INFO
cumcubes.egg-info/SOURCES.txt
cumcubes.egg-info/dependency_links.txt
cumcubes.egg-info/not-zip-safe
cumcubes.egg-info/top_level.txt
cumcubes/include/cumcubes.hpp
cumcubes/include/utils.cuh
cumcubes/src/bindings.cpp
cumcubes/src/cumcubes.cpp
cumcubes/src/cumcubes_kernel.cu